qualesim_quiets/__init__.py
qualesim_quiets/__main__.py
qualesim_quiets/frontend.py
qualesim_quiets/utils.py
qualesim_quiets-1.1.1.data/data/bin/dqcsfeqi
qualesim_quiets-1.1.1.dist-info/LICENSE
qualesim_quiets-1.1.1.dist-info/METADATA
qualesim_quiets-1.1.1.dist-info/WHEEL
qualesim_quiets-1.1.1.dist-info/top_level.txt
qualesim_quiets-1.1.1.dist-info/RECORD
