Metadata-Version: 2.1
Name: qualesim-quiets
Version: 1.1.1
Summary: QuaLeSim frontend for QUIET-S.
Home-page: https://gitee.com/hpcl_quanta/dqcsim-quiets.git
Author: Dingdong Liu
Author-email: dingdongliu@quanta.org.cn
License: GPLv3
Keywords: qualesim quiets
Classifier: Development Status :: 3 - Alpha
Classifier: Intended Audience :: Science/Research
Classifier: License :: OSI Approved :: GNU General Public License v3 (GPLv3)
Classifier: Topic :: Scientific/Engineering
License-File: LICENSE
Requires-Dist: numpy
Requires-Dist: ply
Requires-Dist: pyquiet
